scarlet_schemata/__init__.py
scarlet_schemata/api.py
scarlet_schemata/kafka.py
scarlet_schemata-0.1.4.dist-info/METADATA
scarlet_schemata-0.1.4.dist-info/WHEEL
scarlet_schemata-0.1.4.dist-info/RECORD
